eco/__init__.py
eco/__main__.py
eco/eco_scrapper.py
eco/eco_utils.py
eco_cli-1.3.3.dist-info/LICENSE
eco_cli-1.3.3.dist-info/METADATA
eco_cli-1.3.3.dist-info/WHEEL
eco_cli-1.3.3.dist-info/entry_points.txt
eco_cli-1.3.3.dist-info/top_level.txt
eco_cli-1.3.3.dist-info/RECORD
