Metadata-Version: 2.1
Name: eco-cli
Version: 1.3.3
Summary: A CLI tool for personal finance management
Home-page: https://github.com/martinezpl/eco-cli
Author: Marcin Szleszynski
Author-email: mszlesz@gmail.com
License: MIT
Platform: UNKNOWN
Classifier: Programming Language :: Python :: 3
Classifier: License :: OSI Approved :: MIT License
Classifier: Operating System :: POSIX :: Linux
Requires-Python: >=3.6
Requires-Dist: pandas
Requires-Dist: inquirer
Requires-Dist: bs4
